llm_scratch_lab/__init__.py
llm_scratch_lab/attention.py
llm_scratch_lab/lab.py
llm_scratch_lab/model_utils.py
llm_scratch_lab/tokenizer.py
llm_scratch_lab/transformer.py
llm_scratch_lab/models/gpt.py
llm_scratch_lab-0.0.3.dist-info/licenses/LICENSE
llm_scratch_lab-0.0.3.dist-info/METADATA
llm_scratch_lab-0.0.3.dist-info/WHEEL
llm_scratch_lab-0.0.3.dist-info/top_level.txt
llm_scratch_lab-0.0.3.dist-info/RECORD
