Metadata-Version: 2.4
Name: llm-scratch-lab
Version: 0.0.3
Summary: A toolkit for building an LLM from scratch
Author-email: Frantz Paul <fpaul787@gmail.com>
License-Expression: MIT
Project-URL: Homepage, https://github.com/fpaul787/llm-from-scratch-lab
Project-URL: Issues, https://github.com/fpaul787/llm-from-scratch-lab/issues
Classifier: Programming Language :: Python :: 3
Classifier: Operating System :: OS Independent
Requires-Python: >=3.8
License-File: LICENSE
Requires-Dist: tiktoken>=0.9.0
Requires-Dist: torch>=2.7.0
Requires-Dist: numpy>=2.3.0
Dynamic: license-file
